{
  "vegetarian": false,
  "glutenFree": false,
  "title": "Caribbean Truffle Pie",
  "veryPopular": false,
  "gaps": "no",
  "sourceUrl": "http://www.foodista.com/recipe/355FGG5N/caribbean-truffle-pie",
  "sourceName": "Foodista",
  "vegan": false,
  "sustainable": false,
  "instructions": "<ol><li>Heat oven to 450 degrees. Allow 1 crust pouch to stand at room temperature for 15 to 20 minutes. (Refrigerate remaining crust for a later use.) Remove pie crust from pouch. Unfold crust; remove plastic sheet. Sprinkle with 2 tablespoons coconut; press in lightly. Carefully lift crust off second plastic sheet. Place crust, coconut side up, in 9-inch pie pan; press in bottom and up sides of pan. Flute edge; prick crust generously with fork. Bake at 450 degrees for 9 to 11 minutes or until golden brown. Cool crust while preparing streusel and filling. Reduce oven temperature to 425 degrees.</li><li>In small bowl, combine flour and 1/4 cup sugar. With pastry blender or fork, cut in butter until mixture resembles coarse crumbs. Stir in 1/4 cup coconut. Spread mixture in ungreased shallow baking pan. Bake at 425 degrees for 4 to 8 minutes or until golden brown, stirring every minutes. Set aside.</li><li>In medium saucepan, combine pudding mix, 1/2 cup sugar, lime juice and egg yolks; mix well. Stir in 2 cups water. Cook and stir over medium heat until mixture comes to a full boil. Remove from heat; stir in lime peel. In small bowl, combine white chocolate chips and 1/2 cup of the hot pudding mixture; stir until chips are melted.</li><li>In small bowl, beat cream cheese until light and fluffy. Add white chocolate chip mixture; beat until smooth. Spoon and spread in baked crust. Stir sour cream into remaining pie filling mixture; blend well. Spoon and spread over cream cheese layer. Refrigerate 2 hours or until chilled.</li><li>In small bowl, beat whipping cream until stiff peaks form. Pipe or spoon around edge of pie; garnish with line slices. Sprinkle streusel in center of pie. Store in refrigerator. </li></ol>",
  "aggregateLikes": 1,
  "dairyFree": false,
  "extendedIngredients": [
    {
      "aisle": "Produce",
      "unitLong": "cups",
      "amount": 0.25,
      "unitShort": "c",
      "metaInformation": [],
      "unit": "cup",
      "originalString": "1/4 cup coconut",
      "name": "shredded coconut"
    },
    {
      "aisle": "Produce",
      "unitLong": "tablespoons",
      "amount": 2.0,
      "unitShort": "T",
      "metaInformation": [],
      "unit": "tablespoons",
      "originalString": "2 tablespoons coconut",
      "name": "shredded coconut"
    },
    {
      "aisle": "Cheese",
      "unitLong": "ounces",
      "amount": 8.0,
      "unitShort": "oz",
      "metaInformation": [],
      "unit": "ounce",
      "originalString": "1 package (8 ounce) cream cheese, softened",
      "name": "cream cheese"
    },
    {
      "aisle": "Milk, Eggs, Other Dairy",
      "unitLong": "",
      "amount": 2.0,
      "unitShort": "",
      "metaInformation": [],
      "unit": "",
      "originalString": "2 egg yolks",
      "name": "egg yolk"
    },
    {
      "aisle": "Baking",
      "unitLong": "cups",
      "amount": 0.25,
      "unitShort": "c",
      "metaInformation": [],
      "unit": "cup",
      "originalString": "1/4 cup all-purpose flour",
      "name": "all-purpose flour"
    },
    {
      "aisle": "Milk, Eggs, Other Dairy",
      "unitLong": "cups",
      "amount": 0.5,
      "unitShort": "c",
      "metaInformation": [],
      "unit": "cup",
      "originalString": "1/2 cup heavy whipping cream",
      "name": "heavy whipping cream"
    },
    {
      "aisle": "Baking",
      "unitLong": "ounces",
      "amount": 2.9,
      "unitShort": "oz",
      "metaInformation": [],
      "unit": "ounce",
      "originalString": "1 package (2.9 ounce) lemon pudding mix",
      "name": "lemon pudding mix"
    },
    {
      "aisle": "Produce",
      "unitLong": "slicesslice",
      "amount": 1.0,
      "unitShort": "slicesslices",
      "metaInformation": [],
      "unit": "slicesslices",
      "originalString": "lime slices",
      "name": "lime"
    },
    {
      "aisle": "Produce",
      "unitLong": "tablespoons",
      "amount": 3.0,
      "unitShort": "T",
      "metaInformation": [],
      "unit": "tablespoons",
      "originalString": "3 tablespoons lime juice",
      "name": "lime juice"
    },
    {
      "aisle": "Produce",
      "unitLong": "teaspoon",
      "amount": 1.0,
      "unitShort": "t",
      "metaInformation": [],
      "unit": "teaspoon",
      "originalString": "1 teaspoon grated lime peel",
      "name": "lime zest"
    },
    {
      "aisle": "Refrigerated",
      "unitLong": "ounces",
      "amount": 15.0,
      "unitShort": "oz",
      "metaInformation": [],
      "unit": "ounce",
      "originalString": "1 (15 ounce) refrigerated pie crust",
      "name": "pie crust"
    },
    {
      "aisle": "Milk, Eggs, Other Dairy",
      "unitLong": "tablespoons",
      "amount": 6.0,
      "unitShort": "T",
      "metaInformation": [],
      "unit": "tablespoons",
      "originalString": "6 tablespoons sour cream",
      "name": "sour cream"
    },
    {
      "aisle": "Baking",
      "unitLong": "cups",
      "amount": 0.25,
      "unitShort": "c",
      "metaInformation": [],
      "unit": "cup",
      "originalString": "1/4 cup sugar",
      "name": "granulated sugar"
    },
    {
      "aisle": "Baking",
      "unitLong": "cups",
      "amount": 0.5,
      "unitShort": "c",
      "metaInformation": [],
      "unit": "cup",
      "originalString": "1/2 cup sugar",
      "name": "granulated sugar"
    },
    {
      "aisle": "Milk, Eggs, Other Dairy",
      "unitLong": "teaspoons",
      "amount": 4.0,
      "unitShort": "t",
      "metaInformation": [],
      "unit": "teaspoons",
      "originalString": "4 teaspoons unsalted butter",
      "name": "butter"
    },
    {
      "aisle": "Beverages",
      "unitLong": "cups",
      "amount": 2.0,
      "unitShort": "c",
      "metaInformation": [],
      "unit": "cups",
      "originalString": "2 cups water",
      "name": "water"
    },
    {
      "aisle": "Baking",
      "unitLong": "cup",
      "amount": 1.0,
      "unitShort": "c",
      "metaInformation": [],
      "unit": "cup",
      "originalString": "1 cup white chocolate chips",
      "name": "white chocolate"
    }
  ],
  "readyInMinutes": 150,
  "ketogenic": false,
  "veryHealthy": false,
  "cheap": false,
  "creditText": "Foodista.com – The Cooking Encyclopedia Everyone Can Edit",
  "license": "CC BY 3.0",
  "spoonacularSourceUrl": "https://spoonacular.com/caribbean-truffle-pie-637116",
  "weightWatcherSmartPoints": 30,
  "id": 637116,
  "image": "https://spoonacular.com/recipeImages/Caribbean-Truffle-Pie-637116.jpg",
  "servings": 8,
  "whole30": false,
  "lowFodmap": false
}