{"vegetarian": true, "glutenFree": true, "title": "Greek Side Salad", "veryPopular": false, "gaps": "no", "sourceUrl": "http://www.foodista.com/recipe/QZ2D5V6N/greek-salad", "sourceName": "Foodista", "vegan": false, "sustainable": false, "instructions": "<ol><li> Slice the vegetables into bite-size wedges</li><li>Toss in a bowl with olive oil </li><li>Place feta on top of the salad or break up into crumbles</li></ol>", "aggregateLikes": 3, "dairyFree": false, "extendedIngredients": [{"aisle": "Produce", "unitLong": "", "amount": 1.0, "unitShort": "", "metaInformation": [], "unit": "", "originalString": "1 large cucumber", "name": "cucumber"}, {"aisle": "Oil, Vinegar, Salad Dressing", "unitLong": "servings", "amount": 4.0, "unitShort": "servings", "metaInformation": [], "unit": "servings", "originalString": "high-quality extra-virgin olive oil", "name": "extra-virgin olive oil"}, {"aisle": "Cheese", "unitLong": "pounds", "amount": 0.25, "unitShort": "lb", "metaInformation": [], "unit": "pound", "originalString": "1/4 pound greek feta", "name": "feta"}, {"aisle": "Canned and Jarred", "unitLong": "", "amount": 12.0, "unitShort": "", "metaInformation": [], "unit": "", "originalString": "1 dozen Kalamata olives", "name": "kalamata olives"}, {"aisle": "Produce", "unitLong": "", "amount": 1.0, "unitShort": "", "metaInformation": [], "unit": "", "originalString": "1 large red onion, sliced thinly", "name": "red onion"}, {"aisle": "Produce", "unitLong": "", "amount": 5.0, "unitShort": "", "metaInformation": [], "unit": "", "originalString": "5 large ripe tomatoes", "name": "tomatoes"}], "readyInMinutes": 15, "ketogenic": false, "veryHealthy": false, "cheap": false, "creditText": "Foodista.com \u2013 The Cooking Encyclopedia Everyone Can Edit", "license": "CC BY 3.0", "spoonacularSourceUrl": "https://spoonacular.com/greek-side-salad-645348", "weightWatcherSmartPoints": 8, "id": 645348, "image": "https://spoonacular.com/recipeImages/Greek-Salad-645348.jpg", "servings": 4, "whole30": false, "lowFodmap": false}